hellogrpc/__init__.py
hellogrpc/hellogrpc_pb2.py
hellogrpc/hellogrpc_pb2_grpc.py
hellogrpc-0.2.0.dist-info/DESCRIPTION.rst
hellogrpc-0.2.0.dist-info/METADATA
hellogrpc-0.2.0.dist-info/RECORD
hellogrpc-0.2.0.dist-info/WHEEL
hellogrpc-0.2.0.dist-info/metadata.json
hellogrpc-0.2.0.dist-info/top_level.txt
